sarra/__init__.py
sarra/pyads.py
sarra/sr.py
sarra/sr1.py
sarra/sr_amqp.py
sarra/sr_audit.py
sarra/sr_cache.py
sarra/sr_cfg2.py
sarra/sr_checksum.py
sarra/sr_config.py
sarra/sr_consumer.py
sarra/sr_credentials.py
sarra/sr_file.py
sarra/sr_ftp.py
sarra/sr_http.py
sarra/sr_instances.py
sarra/sr_log2save.py
sarra/sr_message.py
sarra/sr_poll.py
sarra/sr_post.py
sarra/sr_rabbit.py
sarra/sr_report.py
sarra/sr_retry.py
sarra/sr_sarra.py
sarra/sr_sender.py
sarra/sr_sftp.py
sarra/sr_shovel.py
sarra/sr_subscribe.py
sarra/sr_tailf.py
sarra/sr_util.py
sarra/sr_watch.py
sarra/sr_winnow.py
sarra/sr_xattr.py
sarra/examples/cpump/cno_trouble_f00.inc
sarra/examples/poll/aws-nexrad.conf
sarra/examples/poll/podaac_webdav.conf
sarra/examples/poll/pollingest.conf
sarra/examples/poll/pollnoaa.conf
sarra/examples/poll/pollsoapshc.conf
sarra/examples/poll/pollusgs.conf
sarra/examples/poll/pulse.conf
sarra/examples/post/WMO_mesh_post.conf
sarra/examples/sarra/get_podaac_webdav.conf
sarra/examples/sarra/wmo_mesh.conf
sarra/examples/sender/ec2collab.conf
sarra/examples/sender/pitcher_push.conf
sarra/examples/shovel/no_trouble_f00.inc
sarra/examples/subscribe/WMO_Sketch_2mqtt.conf
sarra/examples/subscribe/WMO_Sketch_2v3.conf
sarra/examples/subscribe/WMO_mesh_CMC.conf
sarra/examples/subscribe/WMO_mesh_Peer.conf
sarra/examples/subscribe/aws-nexrad.conf
sarra/examples/subscribe/dd_2mqtt.conf
sarra/examples/subscribe/dd_all.conf
sarra/examples/subscribe/dd_amis.conf
sarra/examples/subscribe/dd_aqhi.conf
sarra/examples/subscribe/dd_cacn_bulletins.conf
sarra/examples/subscribe/dd_citypage.conf
sarra/examples/subscribe/dd_cmml.conf
sarra/examples/subscribe/dd_gdps.conf
sarra/examples/subscribe/dd_ping.conf
sarra/examples/subscribe/dd_radar.conf
sarra/examples/subscribe/dd_rdps.conf
sarra/examples/subscribe/dd_swob.conf
sarra/examples/subscribe/ddc_cap-xml.conf
sarra/examples/subscribe/ddc_normal.conf
sarra/examples/subscribe/downloademail.conf
sarra/examples/subscribe/ec_ninjo-a.conf
metpx_sarracenia-2.24.8.post2.dist-info/AUTHORS.rst
metpx_sarracenia-2.24.8.post2.dist-info/LICENSE.txt
metpx_sarracenia-2.24.8.post2.dist-info/METADATA
metpx_sarracenia-2.24.8.post2.dist-info/WHEEL
metpx_sarracenia-2.24.8.post2.dist-info/entry_points.txt
metpx_sarracenia-2.24.8.post2.dist-info/top_level.txt
metpx_sarracenia-2.24.8.post2.dist-info/RECORD
