Metadata-Version: 2.1
Name: metpx-sarracenia
Version: 2.24.8.post2
Summary: Subscribe, Acquire, and Re-Advertise products.
Home-page: https://github.com/MetPX/sarracenia
Author: Shared Services Canada, Supercomputing, Data Interchange
Author-email: Peter.Silva@canada.ca
License: GPLv2
Platform: UNKNOWN
Classifier: Development Status :: 5 - Production/Stable
Classifier: Environment :: Console
Classifier: Intended Audience :: Developers
Classifier: Intended Audience :: Science/Research
Classifier: Intended Audience :: System Administrators
Classifier: Natural Language :: English
Classifier: License :: OSI Approved :: GNU General Public License v2 (GPLv2)
Classifier: Operating System :: OS Independent
Classifier: Programming Language :: Python :: 3
Classifier: Programming Language :: Python :: 3.5
Classifier: Programming Language :: Python :: 3.6
Classifier: Programming Language :: Python :: 3.7
Classifier: Topic :: Communications :: File Sharing
Classifier: Topic :: System :: Logging
Requires-Dist: amqp
Requires-Dist: appdirs
Requires-Dist: humanize
Requires-Dist: netifaces
Requires-Dist: psutil
Requires-Dist: watchdog
Provides-Extra: poll
Requires-Dist: dateparser ; extra == 'poll'
